{
   "#jiayuan:matrix.org" : 438,
   "#gotosocial-help:superseriousbusiness.org" : 15,
   "#windowssec:grapheneos.org" : 49,
   "#briar:matrix.org" : 9,
   "#grapheneos:grapheneos.org" : 586,
   "#cybersec-offtopic:matrix.org" : 80,
   "#manga:g33k.se" : 4,
   "#lobby:matrix.juggler.jp" : 64,
   "#talk:matrix.fedibird.com" : 1,
   "#otaku:nitro.chat" : 3,
   "#artists-chat:cutefunny.art" : 72,
   "#element-web:matrix.org" : 88,
   "#baseball-watch:matrix.juggler.jp" : 203,
   "#hwl-allgemein:matrix.org" : 2,
   "#memes:anontier.nl" : 14,
   "#retro-game:matrix.juggler.jp" : 15,
   "#neta:matrix.juggler.jp" : 1045,
   "#monero:monero.social" : 133,
   "#syphon:matrix.org" : 23,
   "#lounge:envs.net" : 127,
   "#srad:matrix.juggler.jp" : 979,
   "#epicyon:matrix.libreserver.org" : 5,
   "#selfhosted:matrix.org" : 77,
   "#chat:opensuse.org" : 66,
   "#element-android:matrix.org" : 33,
   "#anime-watch:matrix.juggler.jp" : 2,
   "#miko:matrix.juggler.jp" : 65,
   "#pussthecat.org:pussthecat.org" : 8,
   "#pinebook:matrix.org" : 161,
   "#wetherquake:smith.gdgd.jp.net" : 174,
   "#techloligy:cutefunny.art" : 129,
   "#djt:midov.pl" : 37,
   "#omokan:matrix.juggler.jp" : 126,
   "#tateisu-workshop:matrix.juggler.jp" : 2,
   "#kde:kde.org" : 72,
   "#nheko:nheko.im" : 156,
   "#lounge:cutefunny.art" : 424,
   "#Delta.Chat:matrix.org" : 2,
   "#nerds:the-apothecary.club" : 356,
   "#general-cute:cutefunny.art" : 984,
   "#academianut:matrix.fedibird.com" : 22,
   "#pinetime:matrix.org" : 19,
   "#mollyim:matrix.org" : 6,
   "#HAPPENING:glowers.club" : 231,
   "#godot:feneas.org" : 25,
   "#loli:cutefunny.art" : 239,
   "#trans:the-apothecary.club" : 101,
   "#archlinux:archlinux.org" : 296,
   "#cybersec-privacy:matrix.org" : 9,
   "#offtop:3000.chat" : 9,
   "#privacy-frontends-offtopic:matrix.org" : 205,
   "#teahall:matrix.org" : 1055,
   "#hexavalent:matrix.org" : 10,
   "#envs:envs.net" : 1,
   "#offtopic:grapheneos.org" : 1289,
   "#securemessagingapps:matrix.org" : 154,
   "#chat:techlore.net" : 1869,
   "#sfw:ohai.su" : 50,
   "#linux-hrvatska:matrix.org" : 1,
   "#fluffychat:matrix.org" : 13,
   "#iyh:matrix.juggler.jp" : 17,
   "#vtuber:smith.gdgd.jp.net" : 98,
   "#programming:matrix.juggler.jp" : 9,
   "#gaming:the-apothecary.club" : 25,
   "#soccer:matrix.juggler.jp" : 477,
   "#tools:midov.pl" : 9,
   "#funposting:cutefunny.art" : 46,
   "#cybersecurity:matrix.org" : 4,
   "#omoneta:smith.gdgd.jp.net" : 894,
   "#camera:matrix.juggler.jp" : 48,
   "#python:matrix.org" : 1,
   "#loli-feet:cutefunny.art" : 8,
   "#grey-zone:midov.pl" : 1
}
