{
   "#neta:matrix.juggler.jp" : 1065,
   "#element-web:matrix.org" : 280,
   "#soccer:matrix.juggler.jp" : 189,
   "#retro-game:matrix.juggler.jp" : 8,
   "#nowplaying:matrix.juggler.jp" : 58,
   "#bottom-audio:matrix.juggler.jp" : 1,
   "#money-game:matrix.juggler.jp" : 2,
   "#camera:matrix.juggler.jp" : 47,
   "#moto:smith.gdgd.jp.net" : 11,
   "#miko:matrix.juggler.jp" : 131,
   "#iyh:matrix.juggler.jp" : 10,
   "#academianut:matrix.fedibird.com" : 9,
   "#omoneta:smith.gdgd.jp.net" : 861,
   "#anime-watch:matrix.juggler.jp" : 8,
   "#tateisu-workshop:matrix.juggler.jp" : 1,
   "#subwayTooter:matrix.juggler.jp" : 3,
   "#synapse:matrix.org" : 146,
   "#baseball-watch:matrix.juggler.jp" : 51,
   "#fediverse:nibbana.jp" : 16,
   "#srad:matrix.juggler.jp" : 618,
   "#lobby:matrix.juggler.jp" : 20,
   "#omokan:matrix.juggler.jp" : 103,
   "#beginner:matrix.juggler.jp" : 3,
   "#programming:matrix.juggler.jp" : 12
}
