{
   "#join:g33k.se" : 7,
   "#syphon:matrix.org" : 20,
   "#cybersec-qubes_os:matrix.org" : 13,
   "#omokan:matrix.juggler.jp" : 18,
   "#pinebook:matrix.org" : 134,
   "#selfhosted:matrix.org" : 39,
   "#kde:kde.org" : 59,
   "#cybersec-offtopic:matrix.org" : 233,
   "#neta:matrix.juggler.jp" : 1025,
   "#retro-game:matrix.juggler.jp" : 3,
   "#gotosocial:superseriousbusiness.org" : 4,
   "#HAPPENING:glowers.club" : 412,
   "#miku:matrix.thisisjoes.site" : 3,
   "#teahall:matrix.org" : 554,
   "#off-topic:smith.gdgd.jp.net" : 1,
   "#pc:matrix.juggler.jp" : 30,
   "#lemmy:matrix.org" : 3,
   "#camera:matrix.juggler.jp" : 52,
   "#godot:feneas.org" : 47,
   "#grapheneos:grapheneos.org" : 820,
   "#Delta.Chat:matrix.org" : 4,
   "#nerds:the-apothecary.club" : 260,
   "#securemessagingapps:matrix.org" : 124,
   "#element-android:matrix.org" : 58,
   "#windowssec:grapheneos.org" : 16,
   "#element-web:matrix.org" : 136,
   "#soccer:matrix.juggler.jp" : 93,
   "#mollyim:matrix.org" : 24,
   "#gaiko:smith.gdgd.jp.net" : 3,
   "#jiayuan:matrix.org" : 237,
   "#otaku:nitro.chat" : 3,
   "#casualchat:lolifan.club" : 1,
   "#pinetime:matrix.org" : 42,
   "#baseball-watch:matrix.juggler.jp" : 375,
   "#chat:techlore.net" : 3721,
   "#tateisu-workshop:matrix.juggler.jp" : 1,
   "#wetherquake:smith.gdgd.jp.net" : 110,
   "#cybersecurity:matrix.org" : 135,
   "#monero:monero.social" : 88,
   "#general-cute:cutefunny.art" : 312,
   "#omoneta:smith.gdgd.jp.net" : 840,
   "#nheko:nheko.im" : 181,
   "#fluffychat:matrix.org" : 67,
   "#miko:matrix.juggler.jp" : 52,
   "#lounge:cutefunny.art" : 575,
   "#techloligy:cutefunny.art" : 109,
   "#archlinux:archlinux.org" : 206,
   "#privacy-frontends-offtopic:matrix.org" : 110,
   "#PersonaBBC:matrix.org" : 1,
   "#briar:matrix.org" : 19,
   "#programming:matrix.juggler.jp" : 3,
   "#sfw:sakura.ci" : 184,
   "#anime-watch:matrix.juggler.jp" : 4,
   "#iyh:matrix.juggler.jp" : 18,
   "#djt:midov.pl" : 17,
   "#trans:the-apothecary.club" : 88,
   "#offtop:3000.chat" : 7,
   "#offtopic:grapheneos.org" : 2216,
   "#talk:matrix.fedibird.com" : 237,
   "#vtuber:smith.gdgd.jp.net" : 47,
   "#gaming:the-apothecary.club" : 181,
   "#lounge:envs.net" : 69,
   "#srad:matrix.juggler.jp" : 876,
   "#chat:opensuse.org" : 278,
   "#LemmyJPcommunity:tchncs.de" : 15
}
