{
   "#omo-seijisenkyo:matrix.juggler.jp" : 38,
   "#pro-baseball:matrix.juggler.jp" : 22,
   "#wetherquake:smith.gdgd.jp.net" : 34,
   "#bargain:matrix.juggler.jp" : 197,
   "#news:smith.gdgd.jp.net" : 1550,
   "#freesoftware:matrix.org" : 5,
   "#esora:matrix.fedibird.com" : 4,
   "#omokan:matrix.juggler.jp" : 1,
   "#manga:matrix.juggler.jp" : 4,
   "#football:matrix.juggler.jp" : 29,
   "#keiba:smith.gdgd.jp.net" : 48,
   "#pc:matrix.juggler.jp" : 7,
   "#free-talk:smith.gdgd.jp.net" : 1,
   "#trecking:smith.gdgd.jp.net" : 8,
   "#medium:matrix.juggler.jp" : 133,
   "#vtuber:smith.gdgd.jp.net" : 73,
   "#retro-game:matrix.juggler.jp" : 2,
   "#space:matrix.juggler.jp" : 12,
   "#game-sougou:matrix.juggler.jp" : 31,
   "#camera:matrix.juggler.jp" : 24,
   "#ja-lang-room:nibbana.jp" : 5,
   "#realestate:matrix.juggler.jp" : 35,
   "#omoneta2:smith.gdgd.jp.net" : 749,
   "#mjj:matrix.juggler.jp" : 5
}
