{
   "#keiba:smith.gdgd.jp.net" : 106,
   "#retro-game:matrix.juggler.jp" : 7,
   "#realestate:matrix.juggler.jp" : 179,
   "#off-topic:smith.gdgd.jp.net" : 2,
   "#news-jp:matrix.u-svc.dynv6.net" : 520,
   "#greed:matrix.juggler.jp" : 46,
   "#omoneta2:smith.gdgd.jp.net" : 862,
   "#my-room:smith.gdgd.jp.net" : 9,
   "#omokan:matrix.juggler.jp" : 5,
   "#pro-baseball:matrix.juggler.jp" : 2,
   "#news:smith.gdgd.jp.net" : 3252,
   "#bmw:cutefunny.art" : 7,
   "#anime-commentary:matrix.juggler.jp" : 5,
   "#manga:matrix.juggler.jp" : 3,
   "#tools:midov.pl" : 6,
   "#bargain:matrix.juggler.jp" : 241,
   "#camera:matrix.juggler.jp" : 23,
   "#football:matrix.juggler.jp" : 79,
   "#movie:matrix.juggler.jp" : 13,
   "#academianut:matrix.fedibird.com" : 3,
   "#medium:matrix.juggler.jp" : 53,
   "#moto:smith.gdgd.jp.net" : 8,
   "#wetherquake:smith.gdgd.jp.net" : 147,
   "#pc:matrix.juggler.jp" : 4,
   "#neko:matrix.juggler.jp" : 1,
   "#djt:midov.pl" : 3,
   "#game-sougou:matrix.juggler.jp" : 26,
   "#vtuber:smith.gdgd.jp.net" : 28,
   "#omo-seijisenkyo:matrix.juggler.jp" : 23
}
