{
   "#soccer:matrix.juggler.jp" : 143,
   "#baseball-watch:matrix.juggler.jp" : 308,
   "#element-android:matrix.org" : 22,
   "#vtuber:smith.gdgd.jp.net" : 35,
   "#programming:matrix.juggler.jp" : 3,
   "#hexavalent:matrix.org" : 51,
   "#talk:matrix.fedibird.com" : 62,
   "#Delta.Chat:matrix.org" : 5,
   "#godot:feneas.org" : 7,
   "#securemessagingapps:matrix.org" : 138,
   "#gotosocial:superseriousbusiness.org" : 37,
   "#monkeybusiness:midov.pl" : 2,
   "#offtopic:grapheneos.org" : 1451,
   "#academianut:matrix.fedibird.com" : 13,
   "#ecchi:midov.pl" : 2,
   "#pussthecat.org:pussthecat.org" : 29,
   "#cute:midov.pl" : 7,
   "#pinetime:matrix.org" : 26,
   "#chat:opensuse.org" : 29,
   "#grapheneos:grapheneos.org" : 672,
   "#techloligy:cutefunny.art" : 13,
   "#archlinux:archlinux.org" : 88,
   "#gaiko:smith.gdgd.jp.net" : 2,
   "#jiayuan:matrix.org" : 385,
   "#gotosocial-code:superseriousbusiness.org" : 23,
   "#ajt_news:midov.pl" : 1,
   "#cybersec-qubes_os:matrix.org" : 5,
   "#android:matrix.juggler.jp" : 2,
   "#tools:g33k.se" : 7,
   "#cybersecurity:matrix.org" : 222,
   "#kde:kde.org" : 34,
   "#element-web:matrix.org" : 162,
   "#LemmyJPcommunity:tchncs.de" : 3,
   "#teahall:matrix.org" : 71,
   "#organicmaps:matrix.org" : 25,
   "#ln:nerdsin.space" : 6,
   "#lemmy:matrix.org" : 2,
   "#join:g33k.se" : 10,
   "#neovim:matrix.org" : 57,
   "#briar:matrix.org" : 2,
   "#camera:matrix.juggler.jp" : 65,
   "#omokan:matrix.juggler.jp" : 5,
   "#HAPPENING:glowers.club" : 124,
   "#retro-game:matrix.juggler.jp" : 2,
   "#wotd:midov.pl" : 2,
   "#lobby:matrix.juggler.jp" : 10,
   "#djt:midov.pl" : 25,
   "#neta:matrix.juggler.jp" : 1154,
   "#pinebook:matrix.org" : 228,
   "#sfw:houtworm.im" : 86,
   "#offtop:3000.chat" : 35,
   "#omoneta:smith.gdgd.jp.net" : 999,
   "#anime:cutefunny.art" : 33,
   "#pc:matrix.juggler.jp" : 13,
   "#manga:houtworm.im" : 4,
   "#general-cute:cutefunny.art" : 1337,
   "#privacy-frontends-offtopic:matrix.org" : 272,
   "#srad:matrix.juggler.jp" : 901,
   "#mollyim:matrix.org" : 200,
   "#miko:matrix.juggler.jp" : 182,
   "#wetherquake:smith.gdgd.jp.net" : 203,
   "#otaku:houtworm.im" : 30,
   "#cybersec-offtopic:matrix.org" : 111,
   "#art:houtworm.im" : 180,
   "#nheko:nheko.im" : 100,
   "#PersonaBBC:matrix.org" : 1,
   "#memes:anontier.nl" : 46,
   "#fluffychat:matrix.org" : 40
}
