{
   "#artwork:3000.chat" : 258,
   "#lobby:matrix.juggler.jp" : 2,
   "#lounge:envs.net" : 1,
   "#retro-game:matrix.juggler.jp" : 71,
   "#neta:matrix.juggler.jp" : 822,
   "#cybersec-privacy:matrix.org" : 1,
   "#cybersecurity:matrix.org" : 49,
   "#cybersec-qubes_os:matrix.org" : 27,
   "#matrix:matrix.org" : 283,
   "#vtuber:smith.gdgd.jp.net" : 6,
   "#archlinux:archlinux.org" : 197,
   "#programming:matrix.juggler.jp" : 16,
   "#iyh:matrix.juggler.jp" : 11,
   "#gaiko:smith.gdgd.jp.net" : 1,
   "#offtopic:archlinux.org" : 112,
   "#linux-hrvatska:matrix.org" : 1,
   "#tateisu-workshop:matrix.juggler.jp" : 1,
   "#securemessagingapps:matrix.org" : 189,
   "#camera:matrix.juggler.jp" : 32,
   "#datenschutz:matrix.org" : 1,
   "#freechatcams:matrix.juggler.jp" : 1,
   "#monkeybusiness:midov.pl" : 1,
   "#hexavalent:matrix.org" : 122,
   "#windowssec:grapheneos.org" : 63,
   "#tools:midov.pl" : 8,
   "#mollyim:matrix.org" : 9,
   "#miko:matrix.juggler.jp" : 71,
   "#godot:feneas.org" : 2,
   "#genwebchat:matrix.org" : 434,
   "#mollyim-testing:matrix.org" : 1,
   "#omokan:matrix.juggler.jp" : 11,
   "#selfhosted:matrix.org" : 32,
   "#HAPPENING:glowers.club" : 506,
   "#offtop:3000.chat" : 223,
   "#element-web:matrix.org" : 112,
   "#baseball-watch:matrix.juggler.jp" : 38,
   "#soccer:matrix.juggler.jp" : 20,
   "#grapheneos:grapheneos.org" : 889,
   "#kde:kde.org" : 22,
   "#anime-watch:matrix.juggler.jp" : 2,
   "#Delta.Chat:matrix.org" : 5,
   "#ubuntu:libera.chat" : 388,
   "#srad:matrix.juggler.jp" : 1030,
   "#synapse:matrix.org" : 143,
   "#grey-zone:midov.pl" : 24,
   "#cybersec-offtopic:matrix.org" : 13,
   "#djt:midov.pl" : 28,
   "#envs:envs.net" : 3,
   "#element-translations:matrix.org" : 43,
   "#offtopic:grapheneos.org" : 884
}
