{
   "#akademia:halogen.city" : 162,
   "#omoneta:smith.gdgd.jp.net" : 853,
   "#ai-generated-images:matrix.juggler.jp" : 1,
   "#nsfwRoomList:anontier.nl" : 7,
   "#wotd:midov.pl" : 8,
   "#raspberrypi:matrix.org" : 17,
   "#f**kacademy:smith.gdgd.jp.net" : 15,
   "#lebistrot:matrix.org" : 18,
   "#cybersec-privacy:matrix.org" : 1,
   "#bant:midov.pl" : 283,
   "#talk:reactos.org" : 7,
   "#tateisu-workshop:matrix.juggler.jp" : 1,
   "#soccer:matrix.juggler.jp" : 178,
   "#teahall:matrix.org" : 148,
   "#web3-storage:ipfs.io" : 6,
   "#talk:matrix.fedibird.com" : 9,
   "#Delta.Chat:matrix.org" : 1,
   "#kancore:smith.gdgd.jp.net" : 19,
   "#memes:anontier.nl" : 49,
   "#cybersecurity:matrix.org" : 105,
   "#kde:kde.org" : 204,
   "#element-android:matrix.org" : 55,
   "#AncapBitcoin:matrix.org" : 962,
   "#telegram-foss:matrix.org" : 32,
   "#general-cute:cutefunny.art" : 19,
   "#iyh:matrix.juggler.jp" : 3,
   "#cemetech-programming:taricorp.net" : 2,
   "#ajt_news:midov.pl" : 2,
   "#neta:matrix.juggler.jp" : 1025,
   "#moeyy-mihiyo-all:matrix.org" : 4,
   "#AntiCorruption:matrix.org" : 4,
   "#cybersec-offtopic:matrix.org" : 15,
   "#baseball-watch:matrix.juggler.jp" : 105,
   "#anime:cutefunny.art" : 2,
   "#anime-watch:matrix.juggler.jp" : 2,
   "#music:houtworm.im" : 5,
   "#todcon:cutefunny.art" : 21,
   "#element-web:matrix.org" : 117,
   "#rbrasilivre:matrix.org" : 241,
   "#offtop:nerdsin.space" : 44,
   "#briar:matrix.org" : 15,
   "#weeb-gaming:matrix.org" : 1,
   "#ero:lolifan.club" : 1,
   "#cybersec-qubes_os:matrix.org" : 6,
   "#stonks:iddqd.chat" : 6,
   "#tweens:anontier.nl" : 80,
   "#c:midov.pl" : 250,
   "#osmand#fr:matrix.org" : 41,
   "#development:reactos.org" : 126,
   "#join:g33k.se" : 6,
   "#cute:midov.pl" : 6,
   "#pinephone:matrix.org" : 338,
   "#omokan:matrix.juggler.jp" : 19,
   "#PersonaBBC:matrix.org" : 3,
   "#public:midov.pl" : 2156,
   "#soccer:smith.gdgd.jp.net" : 143,
   "#selfSufficiency:matrix.juggler.jp" : 1,
   "#camera:matrix.juggler.jp" : 3,
   "#Manjaro:matrix.org" : 38,
   "#moto:smith.gdgd.jp.net" : 56,
   "#zoo-straight:cuteworld.space" : 2,
   "#sfw:houtworm.im" : 59,
   "#miko:matrix.juggler.jp" : 48,
   "#vtuber:smith.gdgd.jp.net" : 10,
   "#GEN.POP.CANTINA.:matrix.org" : 794,
   "#HAPPENING:glowers.club" : 372,
   "#djt:midov.pl" : 5,
   "#linux-pl:midov.pl" : 9,
   "#programming:matrix.juggler.jp" : 18,
   "#BRASILACIMADETUDO:matrix.org" : 148,
   "#fdroid:f-droid.org" : 89,
   "#chat:anontier.nl" : 126,
   "#bienvenue:matrix.org" : 2,
   "#randombs3.0:matrix.org" : 1836,
   "#carl:nerdsin.space" : 103,
   "#ecchi:midov.pl" : 16,
   "#godot:feneas.org" : 7,
   "#rabbithole:anontier.nl" : 1085,
   "#uniliber:matrix.org" : 207,
   "#monkeybusiness:midov.pl" : 2,
   "#general:projectsegfau.lt" : 546,
   "#linuxita:matrix.org" : 6,
   "#butter:halogen.city" : 675,
   "#buymore:smith.gdgd.jp.net" : 3,
   "#qubesos.deutsch:matrix.org" : 3,
   "#archlinux:archlinux.org" : 132,
   "#neovim:matrix.org" : 553,
   "#arduinoitalia:matrix.org" : 46,
   "#gaiko:smith.gdgd.jp.net" : 5,
   "#securemessagingapps:matrix.org" : 126,
   "#acmqingchun-talk:comm.cx" : 3,
   "#piracy:plan9.rocks" : 40,
   "#GirlsSelfies:anontier.nl" : 14,
   "#miku:matrix.thisisjoes.site" : 6,
   "#tools:g33k.se" : 2,
   "#odysee-es:matrix.org" : 10,
   "#offtopic:grapheneos.org" : 1129,
   "#moeyy-mihiyo-nsfw:matrix.org" : 1,
   "#camera:smith.gdgd.jp.net" : 3,
   "#twitch_shaknunic:matrix.org" : 2,
   "#OpenSourceAndWeb3:halogen.city" : 18,
   "#learnjapanese:matrix.org" : 1,
   "#linux:matrix.org" : 154,
   "#grapheneos:grapheneos.org" : 503,
   "#firo:matrix.org" : 252,
   "#ipfs-chatter:ipfs.io" : 6
}
