{
   "#manga:midov.pl" : 1,
   "#shotatrap:cutefunny.art" : 51,
   "#resources-daz:cutefunny.art" : 27,
   "#baddads:matrix.org" : 74,
   "#omoneta:matrix.juggler.jp" : 1198,
   "#ch:nerdsin.space" : 11,
   "#TeenNudes:matrix.org" : 3,
   "#raspberrypi:matrix.org" : 6,
   "#western-loli:cutefunny.art" : 45,
   "#realestate:matrix.juggler.jp" : 23,
   "#melhor-cp:matrix.org" : 48,
   "#manga:matrix.juggler.jp" : 7,
   "#Shotacon:lolisho.chat" : 2,
   "#archlinux:archlinux.org" : 1143,
   "#camera:matrix.juggler.jp" : 1,
   "#DarkWebAnonymous:matrix.org" : 1,
   "#3d-loli-other:cutefunny.art" : 6,
   "#AsianIdols:matrix.org" : 8,
   "#tools:midov.pl" : 269,
   "#news-info-data:matrix.fedibird.com" : 10,
   "#cosplayfans:matrix.org" : 7,
   "#pro-baseball:matrix.juggler.jp" : 32,
   "#sfw:nerdsin.space" : 24,
   "#loli:cutefunny.art" : 987,
   "#nlaiporn:cuteworld.space" : 18,
   "#space:matrix.juggler.jp" : 5,
   "#freesoftware:matrix.org" : 232,
   "#g:midov.pl" : 859,
   "#teenjuicy:matrix.org" : 32,
   "#litterbox:plan9.rocks" : 2,
   "#generalchat:cutefunny.art" : 224,
   "#general-bsky:matrix.org" : 2,
   "#bant:midov.pl" : 151,
   "#alyx.rss:matrix.juggler.jp" : 97,
   "#politics:the-apothecary.club" : 17,
   "#tateisu-playing:matrix.juggler.jp" : 10,
   "#greed:matrix.juggler.jp" : 37,
   "#lolibdsm:cutefunny.art" : 3,
   "#djt:midov.pl" : 61,
   "#dadboygay:matrix.org" : 1,
   "#3d-loli-daz:cutefunny.art" : 5,
   "#bargain:matrix.juggler.jp" : 266,
   "#omo-seijisenkyo:matrix.juggler.jp" : 77,
   "#grapheneos:grapheneos.org" : 845,
   "#vtuber:smith.gdgd.jp.net" : 43,
   "#touhou:midov.pl" : 6,
   "#bestiality:cutefunny.art" : 6,
   "#otaku:matrix.org" : 64,
   "#loli-manga:cutefunny.art" : 5,
   "#neko:matrix.juggler.jp" : 1,
   "#HAPPENING:glowers.club" : 19,
   "#offtopic:grapheneos.org" : 1280,
   "#Lavitaebella:nibbana.jp" : 34,
   "#Safe_Wonderland:matrix.org" : 74,
   "#medium:matrix.juggler.jp" : 53,
   "#game-sougou:matrix.juggler.jp" : 16,
   "#bmw:cutefunny.art" : 53,
   "#wetherquake:smith.gdgd.jp.net" : 109,
   "#homoservers:waifuhunter.club" : 23,
   "#omokan:matrix.juggler.jp" : 3,
   "#off-topic:smith.gdgd.jp.net" : 1,
   "#trans:the-apothecary.club" : 72,
   "#element-web:matrix.org" : 71,
   "#guro:hugbox.cc" : 1,
   "#jlss:matrix.org" : 1,
   "#hunter:smith.gdgd.jp.net" : 296,
   "#fate:cutefunny.art" : 1,
   "#YoungFruits:matrix.org" : 2,
   "#element-android:matrix.org" : 32,
   "#news-jp:matrix.u-svc.dynv6.net" : 118,
   "#bluesky-dev:matrix.org" : 20,
   "#anime-commentary:matrix.juggler.jp" : 1,
   "#cute:midov.pl" : 6,
   "#my-room:smith.gdgd.jp.net" : 2,
   "#welcometohellXD:matrix.org" : 400,
   "#news:smith.gdgd.jp.net" : 3495,
   "#fua-and-friends:koneko.chat" : 22,
   "#fedora:fedoraproject.org" : 443,
   "#moto:smith.gdgd.jp.net" : 7,
   "#feral:matrix.ralnet.org" : 12,
   "#linux:matrix.org" : 27,
   "#lolicon:lolisho.chat" : 99,
   "#maphornyjail:cuteworld.space" : 52,
   "#bam:anoncat.top" : 4,
   "#theChildTrainer:cutefunny.art" : 2,
   "#public:midov.pl" : 2536,
   "#red_pill:nerdsin.space" : 39,
   "#programming:matrix.juggler.jp" : 5,
   "#3d-loli-vam:cutefunny.art" : 207,
   "#ipfs-chatter:ipfs.io" : 18,
   "#keiba:smith.gdgd.jp.net" : 20,
   "#todcon:cutefunny.art" : 8,
   "#ptg:matrix.juggler.jp" : 1,
   "#lolicuties-3d:koneko.chat" : 31,
   "#linuxmint-chat:matrix.org" : 5,
   "#web:schildi.chat" : 21,
   "#loli-cub:matrix.ralnet.org" : 4,
   "#offtopic64:matrix.org" : 137,
   "#lolisho.chat:lolisho.chat" : 2,
   "#anime:matrix.org" : 653,
   "#Lolirape:cutefunny.art" : 7,
   "#russian:kde.org" : 418,
   "#alt-loli:cutefunny.art" : 6,
   "#matrix:matrix.org" : 41,
   "#rabbithole:matrix.freyachat.eu" : 686,
   "#talk:cuteworld.space" : 3,
   "#privacy:matrix.anonymousplanet.org" : 23,
   "#football:matrix.juggler.jp" : 37,
   "#randombs3.0:matrix.org" : 1277
}
