{
   "#omokan:matrix.juggler.jp" : 8,
   "#programming:matrix.juggler.jp" : 3,
   "#talk:matrix.fedibird.com" : 2,
   "#pc:matrix.juggler.jp" : 89,
   "#game-sougou:matrix.juggler.jp" : 7,
   "#tv-watch:matrix.juggler.jp" : 1,
   "#realestate:matrix.juggler.jp" : 39,
   "#retro-game:matrix.juggler.jp" : 1,
   "#wetherquake:smith.gdgd.jp.net" : 176,
   "#manga:matrix.juggler.jp" : 2,
   "#vtuber:smith.gdgd.jp.net" : 22,
   "#red_pill:nerdsin.space" : 19,
   "#football:matrix.juggler.jp" : 186,
   "#medium:matrix.juggler.jp" : 82,
   "#pro-baseball:matrix.juggler.jp" : 207,
   "#movie:matrix.juggler.jp" : 3,
   "#keiba:smith.gdgd.jp.net" : 25,
   "#trecking:smith.gdgd.jp.net" : 6,
   "#bant:matrix.fedibird.com" : 19,
   "#omoneta2:smith.gdgd.jp.net" : 948,
   "#camera:matrix.juggler.jp" : 67,
   "#off-topic:smith.gdgd.jp.net" : 1,
   "#bargain:matrix.juggler.jp" : 207,
   "#omo-seijisenkyo:matrix.juggler.jp" : 49,
   "#news:smith.gdgd.jp.net" : 3475,
   "#news-jp:matrix.u-svc.dynv6.net" : 182,
   "#my-room:smith.gdgd.jp.net" : 177,
   "#space:matrix.juggler.jp" : 7,
   "#greed:matrix.juggler.jp" : 105
}
