{
   "#trecking:smith.gdgd.jp.net" : 6,
   "#red_pill:nerdsin.space" : 148,
   "#element-web:matrix.org" : 118,
   "#otaku:matrix.org" : 10,
   "#omo-seijisenkyo:matrix.juggler.jp" : 106,
   "#f**kacademy:smith.gdgd.jp.net" : 12,
   "#music:plan9.rocks" : 15,
   "#wotd:midov.pl" : 9,
   "#medium:matrix.juggler.jp" : 45,
   "#dramaroom:matrix.org" : 4,
   "#camera:matrix.juggler.jp" : 2,
   "#schizo:cutefunny.art" : 14,
   "#pc:matrix.juggler.jp" : 4,
   "#news-jp:matrix.u-svc.dynv6.net" : 726,
   "#jlss:matrix.org" : 3,
   "#general-cute:cutefunny.art" : 263,
   "#retro-game:matrix.juggler.jp" : 7,
   "#kancore:smith.gdgd.jp.net" : 1,
   "#tv-watch:matrix.juggler.jp" : 2,
   "#welcometohellXD:matrix.org" : 2,
   "#anime-commentary:matrix.juggler.jp" : 7,
   "#camera:smith.gdgd.jp.net" : 2,
   "#randombs3.0:matrix.org" : 852,
   "#football:matrix.juggler.jp" : 29,
   "#nsfW:anontier.nl" : 12,
   "#q_and_a:matrix.fedibird.com" : 1,
   "#bmw:cutefunny.art" : 207,
   "#funposting:cutefunny.art" : 10,
   "#game-sougou:matrix.juggler.jp" : 7,
   "#public:midov.pl" : 3597,
   "#tools:midov.pl" : 50,
   "#programming:matrix.juggler.jp" : 12,
   "#HAPPENING:glowers.club" : 248,
   "#buymore:smith.gdgd.jp.net" : 24,
   "#news:smith.gdgd.jp.net" : 3444,
   "#soccer:smith.gdgd.jp.net" : 29,
   "#ajt_news:midov.pl" : 2,
   "#my-room:smith.gdgd.jp.net" : 3,
   "#offtopic:grapheneos.org" : 1303,
   "#linuxmint-chat:matrix.org" : 1,
   "#omoneta:matrix.juggler.jp" : 1041,
   "#bargain:matrix.juggler.jp" : 364,
   "#linux:matrix.juggler.jp" : 54,
   "#trans:the-apothecary.club" : 233,
   "#omokan:matrix.juggler.jp" : 1,
   "#tateisu-playing:matrix.juggler.jp" : 13,
   "#off-topic:smith.gdgd.jp.net" : 1,
   "#djt:midov.pl" : 4,
   "#space:matrix.juggler.jp" : 10,
   "#moto:smith.gdgd.jp.net" : 5,
   "#wetherquake:smith.gdgd.jp.net" : 109,
   "#omoneta:smith.gdgd.jp.net" : 1048,
   "#pc:smith.gdgd.jp.net" : 4,
   "#web:schildi.chat" : 25,
   "#anime:matrix.org" : 36,
   "#realestate:matrix.juggler.jp" : 6,
   "#pro-baseball:matrix.juggler.jp" : 47,
   "#vtuber:smith.gdgd.jp.net" : 5,
   "#greed:matrix.juggler.jp" : 23,
   "#keiba:smith.gdgd.jp.net" : 16,
   "#freesoftware:matrix.org" : 2,
   "#memes:anontier.nl" : 4,
   "#politics:the-apothecary.club" : 12,
   "#linux:matrix.org" : 224
}
