{
   "#element-translations:matrix.org" : 4,
   "#SMT/PersonaBlacked:midov.pl" : 1,
   "#omokan:matrix.juggler.jp" : 5,
   "#camera:matrix.juggler.jp" : 5,
   "#moosic:nerdsin.space" : 4,
   "#cybersec-offtopic:matrix.org" : 241,
   "#anime-watch:matrix.juggler.jp" : 4,
   "#moto:smith.gdgd.jp.net" : 2,
   "#yggmail:matrix.org" : 4,
   "#djt:midov.pl" : 63,
   "#lobby:matrix.juggler.jp" : 10,
   "#tateisu-workshop:matrix.juggler.jp" : 1,
   "#mollyim:matrix.org" : 155,
   "#neta:matrix.juggler.jp" : 843,
   "#selfhosted:matrix.org" : 22,
   "#element-web:matrix.org" : 134,
   "#monkeybusiness:midov.pl" : 2,
   "#wotd:midov.pl" : 5,
   "#LibreShack:midov.pl" : 1,
   "#srad:matrix.juggler.jp" : 937,
   "#cybersecurity:matrix.org" : 180,
   "#vtuber:smith.gdgd.jp.net" : 150,
   "#tools:midov.pl" : 1,
   "#jdrama:midov.pl" : 1,
   "#retro-game:matrix.juggler.jp" : 33,
   "#join:fedoraproject.org" : 1,
   "#HAPPENING:glowers.club" : 693,
   "#godot:feneas.org" : 19,
   "#cybersec-privacy:matrix.org" : 15,
   "#ajt_news:midov.pl" : 1,
   "#baseball-watch:matrix.juggler.jp" : 36,
   "#offtopic:archlinux.org" : 339,
   "#grey-zone:midov.pl" : 66,
   "#japanese:trygve.me" : 83,
   "#windowssec:grapheneos.org" : 12,
   "#omoneta:smith.gdgd.jp.net" : 684,
   "#programming:matrix.juggler.jp" : 23,
   "#hexavalent:matrix.org" : 19,
   "#artwork:3000.chat" : 119,
   "#linux-hrvatska:matrix.org" : 12,
   "#offtop:3000.chat" : 49,
   "#synapse:matrix.org" : 202,
   "#securemessagingapps:matrix.org" : 58,
   "#offtopic:grapheneos.org" : 884,
   "#iyh:matrix.juggler.jp" : 8,
   "#soccer:matrix.juggler.jp" : 140,
   "#grapheneos:grapheneos.org" : 501,
   "#archlinux:archlinux.org" : 185,
   "#3dpd-asian:waifuhunter.club" : 1,
   "#/cumg/:matrix.org" : 30,
   "#3dpd-other:waifuhunter.club" : 5,
   "#miko:matrix.juggler.jp" : 146
}
