{
   "#vtuber:smith.gdgd.jp.net" : 132,
   "#keiba:smith.gdgd.jp.net" : 32,
   "#space:matrix.juggler.jp" : 2,
   "#news:smith.gdgd.jp.net" : 3419,
   "#off-topic:smith.gdgd.jp.net" : 3,
   "#camera:matrix.juggler.jp" : 11,
   "#wetherquake:smith.gdgd.jp.net" : 165,
   "#hunter:smith.gdgd.jp.net" : 2,
   "#omokan:matrix.juggler.jp" : 1,
   "#realestate:matrix.juggler.jp" : 19,
   "#news-jp:matrix.u-svc.dynv6.net" : 569,
   "#omo-seijisenkyo:matrix.juggler.jp" : 60,
   "#bargain:matrix.juggler.jp" : 185,
   "#red_pill:nerdsin.space" : 31,
   "#manga:matrix.juggler.jp" : 12,
   "#football:matrix.juggler.jp" : 149,
   "#mjj:matrix.juggler.jp" : 21,
   "#welcome:matrix.fedibird.com" : 2,
   "#programming:matrix.juggler.jp" : 22,
   "#pro-baseball:matrix.juggler.jp" : 86,
   "#my-room:smith.gdgd.jp.net" : 14,
   "#omoneta2:smith.gdgd.jp.net" : 1054,
   "#lobby:matrix.juggler.jp" : 2,
   "#trecking:smith.gdgd.jp.net" : 6,
   "#medium:matrix.juggler.jp" : 135,
   "#anime-commentary:matrix.juggler.jp" : 1,
   "#greed:matrix.juggler.jp" : 73,
   "#pc:matrix.juggler.jp" : 21
}
