{
   "#tateisu-workshop:matrix.juggler.jp" : 1,
   "#talk:matrix.fedibird.com" : 1,
   "#iyh:matrix.juggler.jp" : 6,
   "#element-web:matrix.org" : 132,
   "#gaiko:smith.gdgd.jp.net" : 4,
   "#pc:matrix.juggler.jp" : 49,
   "#vtuber:smith.gdgd.jp.net" : 9,
   "#miko:matrix.juggler.jp" : 41,
   "#soccer:matrix.juggler.jp" : 365,
   "#baseball-watch:matrix.juggler.jp" : 118,
   "#programming:matrix.juggler.jp" : 13,
   "#anime-watch:matrix.juggler.jp" : 4,
   "#rust-study-jp:matrix.fedibird.com" : 3,
   "#artwork:dfc.world" : 217,
   "#omoneta:smith.gdgd.jp.net" : 806,
   "#djt:midov.pl" : 51,
   "#retro-game:matrix.juggler.jp" : 7,
   "#japanese_study:matrix.org" : 58,
   "#lobby:matrix.juggler.jp" : 28,
   "#neta:matrix.juggler.jp" : 973,
   "#nowplaying:matrix.juggler.jp" : 225,
   "#bottom-audio:matrix.juggler.jp" : 1,
   "#synapse:matrix.org" : 105,
   "#camera:matrix.juggler.jp" : 3,
   "#omokan:matrix.juggler.jp" : 25,
   "#srad:matrix.juggler.jp" : 1132
}
