{
   "#element-web:matrix.org" : 64,
   "#miko:matrix.juggler.jp" : 50,
   "#beginner:matrix.juggler.jp" : 1,
   "#omoneta:smith.gdgd.jp.net" : 202,
   "#iyh:matrix.juggler.jp" : 26,
   "#neta:matrix.juggler.jp" : 247,
   "#omokan:matrix.juggler.jp" : 54,
   "#lobby:matrix.juggler.jp" : 10,
   "#academianut:matrix.fedibird.com" : 1,
   "#synapse:matrix.org" : 120,
   "#anime-watch:matrix.juggler.jp" : 6,
   "#linux:matrix.juggler.jp" : 44,
   "#retro-game:matrix.juggler.jp" : 7,
   "#baseball-watch:matrix.juggler.jp" : 102,
   "#srad:matrix.juggler.jp" : 190,
   "#programming:matrix.juggler.jp" : 2,
   "#soccer:matrix.juggler.jp" : 216
}
