{
   "#baseball-watch:matrix.juggler.jp" : 145,
   "#retro-game:matrix.juggler.jp" : 2,
   "#anime-watch:matrix.juggler.jp" : 3,
   "#nowplaying:matrix.juggler.jp" : 330,
   "#soccer:matrix.juggler.jp" : 118,
   "#camera:matrix.juggler.jp" : 2,
   "#omokan:matrix.juggler.jp" : 27,
   "#neta:matrix.juggler.jp" : 952,
   "#tateisu-workshop:matrix.juggler.jp" : 1,
   "#element-web:matrix.org" : 130,
   "#element-translations:matrix.org" : 11,
   "#moto:smith.gdgd.jp.net" : 1,
   "#srad:matrix.juggler.jp" : 1045,
   "#pc:matrix.juggler.jp" : 5,
   "#omoneta:smith.gdgd.jp.net" : 795,
   "#lobby:matrix.juggler.jp" : 57,
   "#miko:matrix.juggler.jp" : 53,
   "#plaza:nibbana.jp" : 6,
   "#synapse:matrix.org" : 284
}
