{
   "#acmqingchun-setu:comm.cx" : 5,
   "#music:houtworm.im" : 30,
   "#sfw:houtworm.im" : 36,
   "#godot:feneas.org" : 17,
   "#teahall:matrix.org" : 4,
   "#jiayuan:matrix.org" : 1,
   "#lebistrot:matrix.org" : 27,
   "#kde:kde.org" : 62,
   "#anime:cutefunny.art" : 7,
   "#LibreShack:midov.pl" : 22,
   "#retro-game:matrix.juggler.jp" : 5,
   "#camera:smith.gdgd.jp.net" : 24,
   "#HAPPENING:glowers.club" : 34,
   "#mollyim:matrix.org" : 99,
   "#soccer:smith.gdgd.jp.net" : 81,
   "#moeyy-mihiyo-genshin-qa:matrix.org" : 9,
   "#buymore:smith.gdgd.jp.net" : 18,
   "#element-web:matrix.org" : 132,
   "#programming:matrix.juggler.jp" : 1,
   "#neta:matrix.juggler.jp" : 1585,
   "#akademia:halogen.city" : 33,
   "#carl:nerdsin.space" : 77,
   "#Node.js:matrix.org" : 5,
   "#schizo:cutefunny.art" : 1,
   "#baseball-watch:matrix.juggler.jp" : 131,
   "#omoneta:smith.gdgd.jp.net" : 1370,
   "#grapheneos:grapheneos.org" : 428,
   "#briar:matrix.org" : 8,
   "#cybersec-qubes_os:matrix.org" : 91,
   "#otaku:houtworm.im" : 5,
   "#soccer:matrix.juggler.jp" : 92,
   "#memes:anontier.nl" : 21,
   "#briar_desktop:tchncs.de" : 6,
   "#acmqingchun-talk:comm.cx" : 64,
   "#news-info-data:matrix.fedibird.com" : 13,
   "#general-cute:cutefunny.art" : 113,
   "#talk:matrix.fedibird.com" : 10,
   "#element-android:matrix.org" : 26,
   "#PersonaBBC:matrix.org" : 1,
   "#cunnylove:matrix.org" : 7,
   "#p2p:matrix.org" : 8,
   "#f**kacademy:smith.gdgd.jp.net" : 1,
   "#rust:matrix.org" : 192,
   "#ecchi:midov.pl" : 5,
   "#yggmail:matrix.org" : 10,
   "#tools:g33k.se" : 2,
   "#offtopic:grapheneos.org" : 478,
   "#camera:matrix.juggler.jp" : 27,
   "#cute:midov.pl" : 1,
   "#weeb-gaming:matrix.org" : 11,
   "#neovim:matrix.org" : 277,
   "#talk:reactos.org" : 115,
   "#djt:midov.pl" : 11,
   "#lounge:cutefunny.art" : 19,
   "#tateisu-workshop:matrix.juggler.jp" : 1,
   "#moeyy-mihiyo-all:matrix.org" : 1,
   "#miku:matrix.thisisjoes.site" : 3,
   "#lldt-lounge:matrix.org" : 171,
   "#archlinux:archlinux.org" : 281,
   "#cybersec-offtopic:matrix.org" : 100,
   "#tweens:anontier.nl" : 107,
   "#lounge:envs.net" : 244,
   "#miko:matrix.juggler.jp" : 50,
   "#omokan:matrix.juggler.jp" : 38,
   "#help:t2bot.io" : 3,
   "#cybersecurity:matrix.org" : 12,
   "#iyh:matrix.juggler.jp" : 19,
   "#securemessagingapps:matrix.org" : 198,
   "#development:reactos.org" : 8,
   "#wetherquake:smith.gdgd.jp.net" : 166,
   "#vtuber:smith.gdgd.jp.net" : 10
}
