{
   "#mollyim:matrix.org" : 3,
   "#moeyy-mihiyo-nsfw:matrix.org" : 25,
   "#pc:smith.gdgd.jp.net" : 1,
   "#vtuber:smith.gdgd.jp.net" : 9,
   "#miko:matrix.juggler.jp" : 33,
   "#ircjugglerjp:smith.gdgd.jp.net" : 1,
   "#news-info-data:matrix.fedibird.com" : 26,
   "#sfw:houtworm.im" : 34,
   "#pc:matrix.juggler.jp" : 1,
   "#lobby:matrix.juggler.jp" : 2,
   "#wetherquake:smith.gdgd.jp.net" : 133,
   "#acmqingchun-talk:comm.cx" : 1,
   "#tweens:anontier.nl" : 267,
   "#linux-hrvatska:matrix.org" : 6,
   "#soccer:matrix.juggler.jp" : 32,
   "#grapheneos:grapheneos.org" : 594,
   "#cybersec-offtopic:matrix.org" : 8,
   "#development:reactos.org" : 60,
   "#iyh:matrix.juggler.jp" : 5,
   "#ecchi:midov.pl" : 4,
   "#briar_desktop:tchncs.de" : 1,
   "#bienvenue:matrix.org" : 27,
   "#HAPPENING:glowers.club" : 317,
   "#lldt-lounge:matrix.org" : 261,
   "#briar:matrix.org" : 31,
   "#kde:kde.org" : 281,
   "#weeb-gaming:matrix.org" : 1,
   "#omoneta:smith.gdgd.jp.net" : 748,
   "#cybersecurity:matrix.org" : 434,
   "#cybersec-qubes_os:matrix.org" : 3,
   "#neta:matrix.juggler.jp" : 922,
   "#wotd:midov.pl" : 2,
   "#element-android:matrix.org" : 64,
   "#lebistrot:matrix.org" : 24,
   "#lounge:cutefunny.art" : 63,
   "#schizo:cutefunny.art" : 40,
   "#general-cute:cutefunny.art" : 222,
   "#Delta.Chat:matrix.org" : 1,
   "#camera:smith.gdgd.jp.net" : 5,
   "#securemessagingapps:matrix.org" : 35,
   "#p2p:matrix.org" : 4,
   "#rust:matrix.org" : 148,
   "#offtopic:grapheneos.org" : 673,
   "#ubuntu-francophone:matrix.org" : 11,
   "#djt:midov.pl" : 12,
   "#element-web:matrix.org" : 156,
   "#akademia:halogen.city" : 41,
   "#shotatrap:cutefunny.art" : 12,
   "#carl:nerdsin.space" : 675,
   "#cunnylove:matrix.org" : 11,
   "#godot:feneas.org" : 17,
   "#acmqingchun-setu:comm.cx" : 15,
   "#qubesos.deutsch:matrix.org" : 56,
   "#cute:midov.pl" : 1,
   "#camera:matrix.juggler.jp" : 6,
   "#lounge:envs.net" : 274,
   "#memes:anontier.nl" : 26,
   "#talk:matrix.fedibird.com" : 94,
   "#tools:g33k.se" : 9,
   "#PersonaBBC:matrix.org" : 2,
   "#neovim:matrix.org" : 414,
   "#miku:matrix.thisisjoes.site" : 24,
   "#programming:matrix.juggler.jp" : 12,
   "#jiayuan:matrix.org" : 1,
   "#teahall:matrix.org" : 60,
   "#baseball-watch:matrix.juggler.jp" : 336,
   "#f**kacademy:smith.gdgd.jp.net" : 11,
   "#tateisu-workshop:matrix.juggler.jp" : 1,
   "#soccer:smith.gdgd.jp.net" : 27,
   "#otaku:midov.pl" : 1,
   "#ero:lolifan.club" : 2,
   "#anime-watch:matrix.juggler.jp" : 4,
   "#omokan:matrix.juggler.jp" : 20,
   "#buymore:smith.gdgd.jp.net" : 5,
   "#talk:reactos.org" : 83,
   "#archlinux:archlinux.org" : 574
}
