{
   "#cybersec-qubes_os:matrix.org" : 51,
   "#linux-hrvatska:matrix.org" : 1,
   "#lobby:matrix.juggler.jp" : 13,
   "#grapheneos:grapheneos.org" : 726,
   "#godot:feneas.org" : 22,
   "#omoneta:smith.gdgd.jp.net" : 639,
   "#techloligy:cutefunny.art" : 166,
   "#join:g33k.se" : 1,
   "#chat:opensuse.org" : 11,
   "#baseball-watch:matrix.juggler.jp" : 496,
   "#hexavalent:matrix.org" : 10,
   "#cybersecurity:matrix.org" : 217,
   "#advice:g33k.se" : 1,
   "#sfw:houtworm.im" : 50,
   "#pc:matrix.juggler.jp" : 7,
   "#anime:cutefunny.art" : 3,
   "#gotosocial-help:superseriousbusiness.org" : 5,
   "#pinetime:matrix.org" : 38,
   "#camera:matrix.juggler.jp" : 124,
   "#cybersec-offtopic:matrix.org" : 44,
   "#talk:matrix.fedibird.com" : 82,
   "#privacy-frontends-offtopic:matrix.org" : 92,
   "#briar:matrix.org" : 32,
   "#srad:matrix.juggler.jp" : 272,
   "#programming:matrix.juggler.jp" : 60,
   "#offtopic:grapheneos.org" : 1318,
   "#cute:midov.pl" : 13,
   "#lemmy:matrix.org" : 15,
   "#offtop:3000.chat" : 8,
   "#soccer:matrix.juggler.jp" : 139,
   "#pinebook:matrix.org" : 91,
   "#miko:matrix.juggler.jp" : 14,
   "#vtuber:smith.gdgd.jp.net" : 62,
   "#memes:anontier.nl" : 27,
   "#nheko:nheko.im" : 126,
   "#otaku:houtworm.im" : 1,
   "#lounge:cutefunny.art" : 2,
   "#teahall:matrix.org" : 50,
   "#ecchi:midov.pl" : 4,
   "#element-android:matrix.org" : 29,
   "#HAPPENING:glowers.club" : 197,
   "#wetherquake:smith.gdgd.jp.net" : 98,
   "#mollyim:matrix.org" : 31,
   "#djt:midov.pl" : 11,
   "#art:houtworm.im" : 233,
   "#omokan:matrix.juggler.jp" : 17,
   "#pussthecat.org:pussthecat.org" : 48,
   "#neta:matrix.juggler.jp" : 767,
   "#securemessagingapps:matrix.org" : 256,
   "#retro-game:matrix.juggler.jp" : 15,
   "#3dpd-asian:waifuhunter.club" : 3,
   "#gotosocial-code:superseriousbusiness.org" : 33,
   "#fluffychat:matrix.org" : 168,
   "#archlinux:archlinux.org" : 398,
   "#neovim:matrix.org" : 69,
   "#general-cute:cutefunny.art" : 2638,
   "#gotosocial:superseriousbusiness.org" : 152,
   "#element-web:matrix.org" : 98,
   "#tools:g33k.se" : 7,
   "#kde:kde.org" : 57,
   "#jiayuan:matrix.org" : 468,
   "#organicmaps:matrix.org" : 27,
   "#plagueos:matrix.org" : 73
}
