{
   "#ecchi:midov.pl" : 2,
   "#anime:cutefunny.art" : 5,
   "#talk:matrix.fedibird.com" : 8,
   "#cybersec-privacy:matrix.org" : 4,
   "#godot:feneas.org" : 15,
   "#LibreShack:midov.pl" : 1,
   "#securemessagingapps:matrix.org" : 202,
   "#offtopic:grapheneos.org" : 615,
   "#memes:anontier.nl" : 16,
   "#kde:kde.org" : 62,
   "#talk:reactos.org" : 14,
   "#miko:matrix.juggler.jp" : 107,
   "#wetherquake:smith.gdgd.jp.net" : 110,
   "#briar:matrix.org" : 29,
   "#lebistrot:matrix.org" : 25,
   "#f**kacademy:smith.gdgd.jp.net" : 5,
   "#pc:matrix.juggler.jp" : 10,
   "#camera:smith.gdgd.jp.net" : 19,
   "#sfw:houtworm.im" : 68,
   "#HAPPENING:glowers.club" : 32,
   "#android:matrix.juggler.jp" : 5,
   "#cybersecurity:matrix.org" : 234,
   "#general-cute:cutefunny.art" : 412,
   "#lounge:cutefunny.art" : 47,
   "#programming:matrix.juggler.jp" : 5,
   "#development:reactos.org" : 90,
   "#Delta.Chat:matrix.org" : 2,
   "#cybersec-offtopic:matrix.org" : 88,
   "#vtuber:smith.gdgd.jp.net" : 1,
   "#neta:matrix.juggler.jp" : 1312,
   "#carl:nerdsin.space" : 255,
   "#element-android:matrix.org" : 122,
   "#schizo:cutefunny.art" : 468,
   "#srad:matrix.juggler.jp" : 662,
   "#revolt-chat:clustor.net" : 788,
   "#pc:smith.gdgd.jp.net" : 9,
   "#omoneta:smith.gdgd.jp.net" : 1133,
   "#lobby:matrix.juggler.jp" : 5,
   "#art:houtworm.im" : 212,
   "#cybersec-qubes_os:matrix.org" : 84,
   "#osmand#fr:matrix.org" : 46,
   "#baseball-watch:matrix.juggler.jp" : 373,
   "#mollyim:matrix.org" : 15,
   "#ai-generated-images:matrix.juggler.jp" : 542,
   "#gentoo-hardening:matrix.org" : 88,
   "#lldt-lounge:matrix.org" : 548,
   "#omokan:matrix.juggler.jp" : 10,
   "#element-web:matrix.org" : 59,
   "#p2p:matrix.org" : 8,
   "#djt:midov.pl" : 2,
   "#monkeybusiness:midov.pl" : 2,
   "#archlinux:archlinux.org" : 83,
   "#neovim:matrix.org" : 408,
   "#soccer:matrix.juggler.jp" : 173,
   "#grapheneos:grapheneos.org" : 864,
   "#soccer:smith.gdgd.jp.net" : 145,
   "#element-translations:matrix.org" : 5,
   "#cute:midov.pl" : 4,
   "#tools:g33k.se" : 11,
   "#teahall:matrix.org" : 50,
   "#cybersec-whonix:matrix.org" : 48,
   "#ajt_news:midov.pl" : 4,
   "#miku:matrix.thisisjoes.site" : 1,
   "#ircjugglerjp:smith.gdgd.jp.net" : 4,
   "#camera:matrix.juggler.jp" : 21
}
