{
   "#OpenSourceAndWeb3:halogen.city" : 3,
   "#pro-baseball:matrix.juggler.jp" : 36,
   "#off-topic:smith.gdgd.jp.net" : 1,
   "#anime-commentary:matrix.juggler.jp" : 2,
   "#football:matrix.juggler.jp" : 34,
   "#wetherquake:smith.gdgd.jp.net" : 91,
   "#Lavitaebella:nibbana.jp" : 4,
   "#keiba:smith.gdgd.jp.net" : 37,
   "#ward:matrix.juggler.jp" : 21,
   "#manga:matrix.juggler.jp" : 5,
   "#news:smith.gdgd.jp.net" : 3473,
   "#game-sougou:matrix.juggler.jp" : 2,
   "#omoneta2:smith.gdgd.jp.net" : 1248,
   "#realestate:matrix.juggler.jp" : 32,
   "#music:matrix.juggler.jp" : 1,
   "#bargain:matrix.juggler.jp" : 174,
   "#lobby:matrix.juggler.jp" : 7,
   "#vtuber:smith.gdgd.jp.net" : 59,
   "#moto:smith.gdgd.jp.net" : 6,
   "#news-jp:matrix.u-svc.dynv6.net" : 529,
   "#pc:matrix.juggler.jp" : 13,
   "#greed:matrix.juggler.jp" : 18,
   "#omo-seijisenkyo:matrix.juggler.jp" : 16,
   "#medium:matrix.juggler.jp" : 13,
   "#camera:matrix.juggler.jp" : 6
}
