{
   "#djt:midov.pl" : 211,
   "#omoneta:smith.gdgd.jp.net" : 533,
   "#synapse:matrix.org" : 125,
   "#neta:matrix.juggler.jp" : 687,
   "#matrix:matrix.org" : 620,
   "#programming:matrix.juggler.jp" : 85,
   "#baseball-watch:matrix.juggler.jp" : 176,
   "#tateisu-workshop:matrix.juggler.jp" : 1,
   "#jdrama:midov.pl" : 1,
   "#main:iddqd.social" : 1,
   "#iyh:matrix.juggler.jp" : 11,
   "#wotd:midov.pl" : 2,
   "#tools:midov.pl" : 47,
   "#SMT/PersonaBlacked:midov.pl" : 1,
   "#element-web:matrix.org" : 147,
   "#artwork:dfc.world" : 64,
   "#HAPPENING:glowers.club" : 599,
   "#srad:matrix.juggler.jp" : 1064,
   "#offtop:midov.pl" : 43,
   "#public:midov.pl" : 905,
   "#moosic:nerdsin.space" : 26,
   "#retro-game:matrix.juggler.jp" : 6,
   "#miko:matrix.juggler.jp" : 181,
   "#loliNSFW:dfc.world" : 5,
   "#off-topic:smith.gdgd.jp.net" : 1,
   "#gaiko:smith.gdgd.jp.net" : 1,
   "#anime-watch:matrix.juggler.jp" : 1,
   "#nowplaying:matrix.juggler.jp" : 2,
   "#vtuber:smith.gdgd.jp.net" : 78,
   "#tv-watch:matrix.juggler.jp" : 1,
   "#camera:matrix.juggler.jp" : 7,
   "#soccer:matrix.juggler.jp" : 41,
   "#omokan:matrix.juggler.jp" : 71
}
