{
   "#off-topic:smith.gdgd.jp.net" : 1,
   "#pro-baseball:matrix.juggler.jp" : 93,
   "#vtuber:smith.gdgd.jp.net" : 37,
   "#retro-game:matrix.juggler.jp" : 7,
   "#bargain:matrix.juggler.jp" : 211,
   "#bant:matrix.fedibird.com" : 2,
   "#wetherquake:smith.gdgd.jp.net" : 90,
   "#my-room:smith.gdgd.jp.net" : 49,
   "#lobby:matrix.juggler.jp" : 4,
   "#realestate:matrix.juggler.jp" : 42,
   "#red_pill:nerdsin.space" : 8,
   "#omo-seijisenkyo:matrix.juggler.jp" : 36,
   "#keiba:smith.gdgd.jp.net" : 10,
   "#pc:matrix.juggler.jp" : 81,
   "#football:matrix.juggler.jp" : 114,
   "#medium:matrix.juggler.jp" : 66,
   "#omoneta2:smith.gdgd.jp.net" : 873,
   "#game-sougou:matrix.juggler.jp" : 2,
   "#space:matrix.juggler.jp" : 3,
   "#greed:matrix.juggler.jp" : 13,
   "#programming:matrix.juggler.jp" : 9,
   "#moto:smith.gdgd.jp.net" : 1,
   "#movie:matrix.juggler.jp" : 5,
   "#news:smith.gdgd.jp.net" : 3480,
   "#news-jp:matrix.u-svc.dynv6.net" : 494
}
