{
   "#AntiCorruption:matrix.org" : 19,
   "#miko:matrix.juggler.jp" : 74,
   "#butter:halogen.city" : 559,
   "#omokan:matrix.juggler.jp" : 3,
   "#jiayuan:matrix.org" : 1,
   "#cute:midov.pl" : 5,
   "#grapheneos:grapheneos.org" : 728,
   "#kde:kde.org" : 109,
   "#todcon:cutefunny.art" : 27,
   "#fdroid:f-droid.org" : 34,
   "#lebistrot:matrix.org" : 61,
   "#carl:nerdsin.space" : 10,
   "#arduinoitalia:matrix.org" : 43,
   "#camera:smith.gdgd.jp.net" : 1,
   "#cybersec-qubes_os:matrix.org" : 23,
   "#ipfs-chatter:ipfs.io" : 1,
   "#blackMarket:matrix.juggler.jp" : 2,
   "#briar:matrix.org" : 11,
   "#manga:houtworm.im" : 6,
   "#linux-pl:midov.pl" : 3,
   "#ubuntufr:matrix.org" : 10,
   "#talk:reactos.org" : 114,
   "#weeb-gaming:matrix.org" : 3,
   "#BRASILACIMADETUDO:matrix.org" : 196,
   "#djt:midov.pl" : 3,
   "#lounge:cutefunny.art" : 20,
   "#stonks:iddqd.chat" : 2,
   "#qubesos.deutsch:matrix.org" : 2,
   "#cunnylove:matrix.org" : 7,
   "#grey-zone:cuteworld.space" : 268,
   "#plagueos:matrix.org" : 6,
   "#linux:matrix.org" : 241,
   "#omoneta:smith.gdgd.jp.net" : 1090,
   "#kancore:smith.gdgd.jp.net" : 3,
   "#programming:matrix.juggler.jp" : 39,
   "#HAPPENING:glowers.club" : 124,
   "#shotatrap:cutefunny.art" : 3,
   "#web3-storage:ipfs.io" : 3,
   "#cemetech-programming:taricorp.net" : 17,
   "#soccer:matrix.juggler.jp" : 1682,
   "#firo:matrix.org" : 102,
   "#camera:matrix.juggler.jp" : 2,
   "#nsfwRoomList:anontier.nl" : 73,
   "#element-android:matrix.org" : 75,
   "#telegram-foss:matrix.org" : 10,
   "#raspberrypi:matrix.org" : 10,
   "#general-cute:cutefunny.art" : 164,
   "#uniliber:matrix.org" : 64,
   "#memes:anontier.nl" : 1,
   "#vtuber:smith.gdgd.jp.net" : 14,
   "#pinephone:matrix.org" : 339,
   "#cybersec-offtopic:matrix.org" : 17,
   "#GEN.POP.CANTINA.:matrix.org" : 864,
   "#iyh:matrix.juggler.jp" : 13,
   "#baseball-watch:matrix.juggler.jp" : 32,
   "#ecchi:midov.pl" : 7,
   "#akademia:halogen.city" : 439,
   "#teahall:matrix.org" : 18,
   "#retro-game:matrix.juggler.jp" : 5,
   "#odysee-es:matrix.org" : 7,
   "#acmqingchun-talk:comm.cx" : 2,
   "#rabbithole:anontier.nl" : 435,
   "#Delta.Chat:matrix.org" : 1,
   "#general:projectsegfau.lt" : 393,
   "#public:midov.pl" : 5057,
   "#osmand#fr:matrix.org" : 9,
   "#Manjaro:matrix.org" : 18,
   "#monkeybusiness:midov.pl" : 4,
   "#tools:g33k.se" : 1,
   "#sfw:houtworm.im" : 59,
   "#buymore:smith.gdgd.jp.net" : 10,
   "#GirlsSelfies:anontier.nl" : 3,
   "#offtop:nerdsin.space" : 67,
   "#AncapBitcoin:matrix.org" : 94,
   "#pc:matrix.juggler.jp" : 10,
   "#moosic:nerdsin.space" : 3,
   "#rbrasilivre:matrix.org" : 431,
   "#grey-zone-social:cuteworld.space" : 316,
   "#cybersecurity:matrix.org" : 26,
   "#tv-watch:matrix.juggler.jp" : 13,
   "#offtopic:grapheneos.org" : 596,
   "#piracy:plan9.rocks" : 7,
   "#talk:matrix.fedibird.com" : 5,
   "#OpenSourceAndWeb3:halogen.city" : 2,
   "#development:reactos.org" : 63,
   "#tateisu-workshop:matrix.juggler.jp" : 2,
   "#bant:midov.pl" : 145,
   "#moto:smith.gdgd.jp.net" : 66,
   "#neovim:matrix.org" : 508,
   "#anime:cutefunny.art" : 9,
   "#tweens:anontier.nl" : 64,
   "#selfSufficiency:matrix.juggler.jp" : 1,
   "#soccer:smith.gdgd.jp.net" : 1572,
   "#neta:matrix.juggler.jp" : 1217,
   "#archlinux:archlinux.org" : 180,
   "#PersonaBBC:matrix.org" : 1,
   "#f**kacademy:smith.gdgd.jp.net" : 33,
   "#pc:smith.gdgd.jp.net" : 8,
   "#news-info-data:matrix.fedibird.com" : 4,
   "#element-web:matrix.org" : 198,
   "#godot:feneas.org" : 1,
   "#twitch_shaknunic:matrix.org" : 1,
   "#mollyim:matrix.org" : 115,
   "#securemessagingapps:matrix.org" : 9
}
